auto_ts/__init__.py
auto_ts/__version__.py
auto_ts/py.typed
auto_ts/models/__init__.py
auto_ts/models/build_base.py
auto_ts/models/build_ml.py
auto_ts/models/build_prophet.py
auto_ts/models/build_pyflux.py
auto_ts/models/ml_models.py
auto_ts/models/ar_based/__init__.py
auto_ts/models/ar_based/build_arima.py
auto_ts/models/ar_based/build_arima_base.py
auto_ts/models/ar_based/build_autoarimax.py
auto_ts/models/ar_based/build_sarimax.py
auto_ts/models/ar_based/build_var.py
auto_ts/models/ar_based/param_finder.py
auto_ts/test/__init__.py
auto_ts/test/test_auto_sarimax.py
auto_ts/test/test_auto_ts.py
auto_ts/test/test_var.py
auto_ts/utils/__init__.py
auto_ts/utils/colors.py
auto_ts/utils/eda.py
auto_ts/utils/etl.py
auto_ts/utils/logging.py
auto_ts/utils/metrics.py
auto_ts/utils/my_encoders.py
auto_ts/utils/val.py
auto_ts-0.0.92.dist-info/LICENSE
auto_ts-0.0.92.dist-info/METADATA
auto_ts-0.0.92.dist-info/WHEEL
auto_ts-0.0.92.dist-info/top_level.txt
auto_ts-0.0.92.dist-info/RECORD
