Metadata-Version: 2.1
Name: auto_ts
Version: 0.0.92
Summary: Automatically Build Multiple Time Series models fast - now with Facebook Prophet!
Home-page: https://github.com/AutoViML/Auto_TS
Author: Ram Seshadri
License: Apache License 2.0
Classifier: Programming Language :: Python :: 3
Classifier: Operating System :: OS Independent
License-File: LICENSE
Requires-Dist: ipython
Requires-Dist: jupyter
Requires-Dist: pmdarima
Requires-Dist: numpy
Requires-Dist: xlrd
Requires-Dist: pandas
Requires-Dist: matplotlib
Requires-Dist: seaborn
Requires-Dist: prophet
Requires-Dist: scikit-learn (>=0.24.0)
Requires-Dist: statsmodels
Requires-Dist: xgboost (>=2.0)
Requires-Dist: prettytable
Requires-Dist: dask (>=2022.1.0)
Requires-Dist: pyyaml (>=5.4.1)
Requires-Dist: GPUtil (>=1.4.0)
Requires-Dist: distributed (>=2022.2.0)
